[1,["ecpdLyjvZBwrvm+cedCcQy","f6I1QZ+ghGjo4P9vfn91X0","55besRVNFAuozmrhIGOLrY","e97GVMl6JHh5Ml5qEDdSGa","f0BIwQ8D5Ml7nTNQbh1YlS","29FYIk+N1GYaeWH/q1NxQO","a2MjXRFdtLlYQ5ouAFv/+R","ddBcV/Ix9CCquoH575i4Rw","130e7b646"],["node","_parent","_spriteFrame","_N$normalSprite","_N$pressedSprite","_N$hoverSprite","_N$disabledSprite","root","data","_textureSetter"],[["cc.Node",["_name","_opacity","_prefab","_contentSize","_components","_parent","_trs","_children","_color"],1,4,5,9,1,7,2,5],["cc.Widget",["_alignFlags","_originalWidth","_originalHeight","alignMode","_top","_bottom","node"],-3,1],["cc.Layout",["_resize","_N$layoutType","_N$paddingLeft","_N$spacingX","node","_layoutSize"],-1,1,5],["cc.Sprite",["_sizeMode","_srcBlendFactor","_type","node","_materials","_spriteFrame"],0,1,3,6],["cc.PrefabInfo",["fileId","root","asset"],2,1,1],["cc.Label",["_string","_fontSize","_lineHeight","_N$verticalAlign","_N$horizontalAlign","_N$overflow","_enableWrapText","_N$cacheMode","node","_materials"],-5,1,3],"cc.SpriteFrame",["cc.Prefab",["_name"],2],["cc.Node",["_name","_parent","_children","_components","_prefab","_contentSize"],2,1,12,9,4,5],["3e4dbye7vFONrXLaKYLrmxF",["skinPage","node","nodes"],2,1,9],["SkinNode",["skinKey","nodes"],2,2],["21f54HPUqVLeqr+HTQBotcO",["node"],3,1],["cc.BlockInputEvents",["node"],3,1],["41ebaVoPpRA4Kp67XEdHfZn",["i18n_string","node"],2,1],["cc.Button",["node","clickEvents","_N$normalColor","_N$pressedColor","_N$disabledColor","_N$target","_N$normalSprite","_N$pressedSprite","_N$hoverSprite","_N$disabledSprite"],3,1,9,5,5,5,1,6,6,6,6],["cc.ClickEvent",["_componentId","handler","target"],1,1]],[[4,0,1,2,2],[10,0,1,2],[0,0,5,2,3,6,2],[13,0,1,2],[0,0,5,4,2,8,3,6,2],[0,0,5,7,4,2,3,6,2],[0,0,5,4,2,3,6,2],[3,1,2,0,3,4,5,4],[5,0,1,2,4,3,5,8,9,7],[5,0,1,2,6,3,7,8,9,7],[14,0,1,2,3,4,5,6,7,8,9,1],[15,0,1,2,3],[7,0,2],[0,0,7,4,2,3,6,2],[0,0,4,2,8,3,2],[0,0,1,5,4,2,8,3,3],[0,0,5,7,4,2,3,2],[0,0,7,4,2,3,2],[8,0,1,2,3,4,5,2],[1,0,6,2],[1,3,0,1,2,6,5],[1,0,4,5,1,2,6,6],[9,0,1,2,2],[11,0,1],[4,1,2,1],[2,0,1,4,5,3],[2,0,1,2,3,4,5,5],[2,0,1,2,4,5,4],[3,0,3,4,5,2],[3,3,4,5,1],[12,0,1]],[[[[12,"GameGrade"],[13,"GameGrade",[-12,-13],[[19,45,-2],[22,"gradeGame",-10,[[1,"title",[-3]],[1,"like",[-4]],[1,"light-btn-bg",[-5]],[1,"light-btn-info",[-6,-7]],[1,"nomor-btn-info",[-8]],[1,"bg",[-9]]]],[23,-11]],[24,-1,0],[5,750,1334],[375,667,0,0,0,0,1,1,1,1]],[18,"New Layout",1,[[[2,"New Node",-16,[0,"6eACNM7zZK9LzmxVcrFZge",1,0],[5,0,58],[0,217.99,0,0,0,0,1,1,1,1]],-17,[2,"New Node",-18,[0,"12apkbDC9OIp/zZUXDHyZx",1,0],[5,0,32],[0,116.29000000000002,0,0,0,0,1,1,1,1]],-19,[2,"New Node",-20,[0,"fcN4yKMYVAGKRY8R2ub3MU",1,0],[5,0,50],[0,40.01000000000002,0,0,0,0,1,1,1,1]],-21,[2,"New Node",-22,[0,"385btEb1tBXJWeq59j2+QY",1,0],[5,0,30],[0,-85.98999999999998,0,0,0,0,1,1,1,1]],-23,[2,"New Node",-24,[0,"dbME7KsxZI84Wdw+uGq9Sd",1,0],[5,0,60],[0,-216.98999999999998,0,0,0,0,1,1,1,1]]],4,1,4,1,4,1,4,1,4],[[25,1,2,-14,[5,560,493.98]],[7,1,1,0,-15,[18],19]],[0,"ddPmseXX9AyqiM73fY5unK",1,0],[5,560,493.98]],[14,"Background",[[7,1,1,0,-25,[4],5],[20,0,45,100,40,-26]],[0,"1aKvpl3MtKaaxpjjg5tZDj",1,0],[4,4294083874],[5,450,86]],[15,"New Sprite(Splash)",106,1,[[28,0,-27,[0],1],[21,45,-300,-300,100,709,-28],[30,-29]],[0,"cdt6221x5BXZjGveWV5h+l",1,0],[4,4278190080],[5,750,1934]],[4,"New Label",2,[[8,"评价我们",42,45,1,1,3,-30,[2]],[3,"评价-标题",-31]],[0,"e4o4Q97gVC9reUmOz7jDhB",1,0],[4,4278190080],[5,500,56.7],[0,160.64000000000001,0,0,0,0,1,1,1,1]],[4,"New Label",2,[[8,"你喜欢数独吗？",28,28,1,1,3,-32,[3]],[3,"评价-你喜欢数独吗",-33]],[0,"8aX+JuP5tB7q7tNdbjgmUw",1,0],[4,4286611584],[5,500,35.28],[0,82.65000000000002,0,0,0,0,1,1,1,1]],[5,"RectBtn",2,[3,-35],[[10,-34,[[11,"21f54HPUqVLeqr+HTQBotcO","onYesBtnClick",1]],[4,4293322470],[4,4291348680],[4,3363338360],3,9,10,11,12]],[0,"e51TNVKrhKZr3IUdz6AHp6",1,0],[5,450,86],[0,-27.98999999999998,0,0,0,0,1,1,1,1]],[16,"New Layout",7,[-37,-38],[[26,1,1,20,10,-36,[5,96,86]]],[0,"88k6slqq5Dgq0fSAykfj+x",1,0],[5,96,86]],[6,"Label",8,[[9,"是",30,30,false,1,1,-39,[8]],[3,"评价-是",-40]],[0,"8bNO20GWhIRYawAHndrgL5",1,0],[5,30,37.8],[33,0,0,0,0,0,1,1,1,1]],[17,"New Layout",[-42],[[27,1,1,20,-41,[5,50,86]]],[0,"1bz3e40jZKu4cy3eSwlaEi",1,0],[5,50,86]],[4,"Label",10,[[9,"否",30,30,false,1,1,-43,[13]],[3,"评价-否",-44]],[0,"5dea1RwEdGe6x+Rf5rD9VX",1,0],[4,4281545523],[5,30,37.8],[10,0,0,0,0,0,1,1,1,1]],[6,"evaluate-like-icon",8,[[29,-45,[6],7]],[0,"2c+Wit2thL96o970pGwQCQ",1,0],[5,36,36],[-10,-0.258,0,0,0,0,1,1,1,1]],[5,"RectBtn",2,[10],[[10,-46,[[11,"21f54HPUqVLeqr+HTQBotcO","onNoBtnClick",1]],[4,4293322470],[4,4291348680],[4,3363338360],10,14,15,16,17]],[0,"83zYM8xlBGuqy4xgwy19pq",1,0],[5,450,86],[0,-143.98999999999998,0,0,0,0,1,1,1,1]]],0,[0,7,1,0,0,1,0,-1,5,0,-1,6,0,-1,3,0,-1,12,0,-2,9,0,-1,11,0,-1,2,0,0,1,0,0,1,0,-1,4,0,-2,2,0,0,2,0,0,2,0,1,2,0,-2,5,0,1,2,0,-4,6,0,1,2,0,-6,7,0,1,2,0,-8,13,0,1,2,0,0,3,0,0,3,0,0,4,0,0,4,0,0,4,0,0,5,0,0,5,0,0,6,0,0,6,0,0,7,0,-2,8,0,0,8,0,-1,12,0,-2,9,0,0,9,0,0,9,0,0,10,0,-1,11,0,0,11,0,0,11,0,0,12,0,0,13,0,8,1,3,1,7,10,1,13,46],[0,0,0,0,0,0,0,0,0,0,0,0,0,0,0,0,0,0,0,0],[-1,2,-1,-1,-1,2,-1,2,-1,3,4,5,6,-1,3,4,5,6,-1,2],[0,6,0,0,0,1,0,7,0,2,3,4,5,0,2,3,4,5,0,1]],[[{"name":"evaluate-like-icon","rect":[556,985,36,36],"offset":[0,0],"originalSize":[36,36],"capInsets":[0,0,0,0]}],[6],0,[0],[9],[8]]]]